mccolors/__init__.py
mccolors/colors.py
mccolors/mc.py
mccolors/mc_color_handler.py
mccolors-0.1.dist-info/LICENSE
mccolors-0.1.dist-info/METADATA
mccolors-0.1.dist-info/WHEEL
mccolors-0.1.dist-info/top_level.txt
mccolors-0.1.dist-info/RECORD
