Metadata-Version: 2.1
Name: mccolors
Version: 0.1
Summary: A Python package for managing Minecraft-style colors in terminal output.
Home-page: https://github.com/wrrulos/mccolors
Author: wRRulos
Author-email: vegapedroagustin@gmail.com
License: MIT License
Classifier: Programming Language :: Python :: 3
Classifier: Operating System :: OS Independent
License-File: LICENSE
